.travis.yml
README.rst
bootstrap.py
buildout.cfg
setup.cfg
setup.py
travis.cfg
docs/HISTORY.rst
docs/INSTALL.txt
docs/LICENSE.GPL
docs/LICENSE.txt
quintagroup/__init__.py
quintagroup.megamenu.egg-info/PKG-INFO
quintagroup.megamenu.egg-info/SOURCES.txt
quintagroup.megamenu.egg-info/dependency_links.txt
quintagroup.megamenu.egg-info/entry_points.txt
quintagroup.megamenu.egg-info/namespace_packages.txt
quintagroup.megamenu.egg-info/not-zip-safe
quintagroup.megamenu.egg-info/requires.txt
quintagroup.megamenu.egg-info/top_level.txt
quintagroup/megamenu/__init__.py
quintagroup/megamenu/configure.zcml
quintagroup/megamenu/tests.py
quintagroup/megamenu/browser/__init__.py
quintagroup/megamenu/browser/configure.zcml
quintagroup/megamenu/browser/resources.zcml
quintagroup/megamenu/browser/sections.py
quintagroup/megamenu/browser/resources/megamenu.css
quintagroup/megamenu/browser/resources/megamenu.js
quintagroup/megamenu/browser/templates/sections.pt
quintagroup/megamenu/interfaces/__init__.py
quintagroup/megamenu/interfaces/quintagroupmegamenulayer.py
quintagroup/megamenu/locales/uk/LC_MESSAGES/README.txt
quintagroup/megamenu/profiles/default/browserlayer.xml
quintagroup/megamenu/profiles/default/cssregistry.xml
quintagroup/megamenu/profiles/default/jsregistry.xml
quintagroup/megamenu/profiles/default/metadata.xml