Metadata-Version: 1.0
Name: quintagroup.megamenu
Version: 1.5.3
Summary: Mega menu for Plone
Home-page: https://github.com/quintagroup/quintagroup.megamenu/
Author: Quintagroup
Author-email: support@quintagroup.com
License: GPL
Keywords: menu mega panels
Platform: UNKNOWN
Classifier: Framework :: Plone
Classifier: Framework :: Plone :: 3.2
Classifier: Framework :: Plone :: 3.3
Classifier: Framework :: Plone :: 4.0
Classifier: Framework :: Plone :: 4.1
Classifier: Framework :: Plone :: 4.2
Classifier: Framework :: Plone :: 4.3
Classifier: Framework :: Zope2
Classifier: Framework :: Zope3
Classifier: Programming Language :: Python
Classifier: Topic :: Software Development :: Libraries :: Python Modules
Classifier: License :: OSI Approved :: GNU General Public License (GPL)
Classifier: Topic :: Internet :: WWW/HTTP :: Dynamic Content
Classifier: Operating System :: OS Independent
Classifier: Development Status :: 5 - Production/Stable
